Workbook

Sheet Summary
A1: Pete Crow-Armstrong, six years and $115 million: what it is actually worth
A2: All figures in millions of dollars, present value as of 2026. Change anything on the Assumptions tab and these move.
A4: What the Cubs pay
A5: Guarantee, nominal | B5: =SUM(Model!G5:G10)+Assumptions!B6 -> 115 | C5: Six salaries plus the signing bonus.
A6: Guarantee, present value at 2026 | B6: =SUMPRODUCT(Model!G5:G10,Model!K5:K10)+Assumptions!B6 -> 91.138554 | C6: The schedule is backloaded, which is worth real money and is invisible in the average annual value.
A7: Average annual value | B7: =SUM(Model!G5:G10)/6+Assumptions!B6/6 -> 19.166667 | C7: A competitive balance tax concept, not an economic one.
A9: Question A: was he worth it?
A10: Market value of projected production | B10: =SUM(Model!F5:F10) -> 361.3664 | C10: Projected WAR times the market rate per win.
A11: Surplus value, present value | B11: =SUM(Model!L5:L10)-Assumptions!B6 -> 205.93521 | C11: Value produced minus salary paid. This is the number that makes every young star's deal look like a steal.
A13: Question B: was the extension itself a good decision?
A14: Cost with no extension, present value | B14: =SUMPRODUCT(Model!H5:H10,Model!K5:K10) -> 119.68955 | C14: What the Cubs would have paid anyway through the control years, plus a free agent deal for 2031 and 2032.
A15: Savings from the extension, present value | B15: =SUM(Model!M5:M10)-Assumptions!B6 -> 28.550996 | C15: The only number that measures the decision the front office actually made.
A16: of which the control years, 2027 to 2030 | B16: =SUM(Model!M5:M8)-Assumptions!B6 -> 19.115605 | C16: Arbitration, where most of the value turns out to be.
A17: of which the bought out free agent years, 2031 and 2032 | B17: =SUM(Model!M9:M10) -> 9.4353913 | C17: The part every write-up leads with.
A19: The gap between line 11 and line 15 is the whole argument.
A20: Both are correct. The first says he is producing far more than he is paid, which is true of nearly every pre-free-agency star and says little about the front office. The second says what the Cubs gained by signing in March 2026 rather than waiting, which is the decision under review.
A22: Not modeled: the MVP escalators on the 2031 and 2032 bases, which run off 2027 through 2031 voting only, so the 2026 award triggers nothing. The $1 million assignment bonus on any trade. The pre-arbitration bonus pool. Off-field revenue. And the largest omission of all, a salary cap, which would reset both the market rate per win and the free agent counterfactual at once.

Sheet Assumptions
A1: Pete Crow-Armstrong extension model | assumptions
A2: Blue cells are inputs. Change them and every other tab recalculates. Yellow marks the three that move the answer most.
A4: Contract facts (do not change)
A5: Extension guarantee ($M) | B5: 115 | C5: AP and MLB.com, March 24 2026. Six years, 2027 through 2032, no club options.
A6: Signing bonus ($M) | B6: 5 | C6: Payable by May 15 2026.
A7: Service time at signing | B7: 1.17 | C7: Spotrac / Baseball Reference, January 2026. Free agency would have followed the 2030 season.
A8: Base year for discounting | B8: 2026 | C8: All present values are stated as of 2026.
A10: Performance and market assumptions
A11: True talent WAR entering 2027 (age 25) | B11: 6.5 | C11: Regressed estimate, not the 2026 result. A 10.0 WAR season regresses heavily. Single most important input.
A12: Market rate per win in 2027 ($M) | B12: 9 | C12: Open market clearing price for one win. Industry estimates have run $8M to $10M. Top of market runs higher.
A13: Annual inflation in $ per win | B13: 0.03 | C13: Applied from 2027 forward.
A14: Discount rate | B14: 0.06 | C14: Club cost of capital. Backloaded money is worth less.
A15: 2027 pre-arbitration salary, no extension ($M) | B15: 1 | C15: Renewal near the minimum. Excludes the pre-arbitration bonus pool, whose survival past the CBA is unknown.
A16: Arbitration 1 share of open market value | B16: 0.25 | C16: 2028. Conventional 25/40/60 arbitration ladder.
A17: Arbitration 2 share of open market value | B17: 0.4 | C17: 2029.
A18: Arbitration 3 share of open market value | B18: 0.6 | C18: 2030.
A19: Hypothetical free agent deal, length in years | B19: 8 | C19: Signed after 2030, covering ages 29 through 36.
A20: Share of projected value an elite free agent captures | B20: 1 | C20: 1.00 means he signs for exactly his projected value. Above 1.00 means the top of the market pays a premium.
A22: Aging curve: WAR added to true talent, by age | C22: Peak at 26 and 27, then decline. Steeper than a slugger's curve because this player's value leans on defense and speed.
A23: Age | B23: Delta WAR
A24: 25 | B24: 0
A25: 26 | B25: 0.3
A26: 27 | B26: 0.3
A27: 28 | B27: -0.1
A28: 29 | B28: -0.7
A29: 30 | B29: -1.4
A30: 31 | B30: -2.1
A31: 32 | B31: -2.8
A32: 33 | B32: -3.5
A33: 34 | B33: -4.2
A34: 35 | B34: -4.9
A35: 36 | B35: -5.6

Sheet FA deal
A1: Counterfactual free agent contract he would have signed after 2030
A2: Absent the extension he reaches free agency at 28. A long deal's annual value is set by the whole term, including the decline years, so the 2031 and 2032 counterfactual is this deal's average annual value, not a single season's worth.
A4: Year | B4: Age | C4: Projected WAR | D4: $ per win ($M) | E4: Market value ($M)
A5: 2031 | B5: =29+A5-2031 -> 29 | C5: =MAX(0,Assumptions!$B$11+INDEX(Assumptions!$A$24:$B$35,MATCH(B5,Assumptions!$A$24:$A$35,0),2)) -> 5.8 | D5: =Assumptions!$B$12*(1+Assumptions!$B$13)^(A5-2027) -> 10.129579 | E5: =C5*D5 -> 58.75156
A6: 2032 | B6: =29+A6-2031 -> 30 | C6: =MAX(0,Assumptions!$B$11+INDEX(Assumptions!$A$24:$B$35,MATCH(B6,Assumptions!$A$24:$A$35,0),2)) -> 5.1 | D6: =Assumptions!$B$12*(1+Assumptions!$B$13)^(A6-2027) -> 10.433467 | E6: =C6*D6 -> 53.21068
A7: 2033 | B7: =29+A7-2031 -> 31 | C7: =MAX(0,Assumptions!$B$11+INDEX(Assumptions!$A$24:$B$35,MATCH(B7,Assumptions!$A$24:$A$35,0),2)) -> 4.4 | D7: =Assumptions!$B$12*(1+Assumptions!$B$13)^(A7-2027) -> 10.746471 | E7: =C7*D7 -> 47.284471
A8: 2034 | B8: =29+A8-2031 -> 32 | C8: =MAX(0,Assumptions!$B$11+INDEX(Assumptions!$A$24:$B$35,MATCH(B8,Assumptions!$A$24:$A$35,0),2)) -> 3.7 | D8: =Assumptions!$B$12*(1+Assumptions!$B$13)^(A8-2027) -> 11.068865 | E8: =C8*D8 -> 40.9548
A9: 2035 | B9: =29+A9-2031 -> 33 | C9: =MAX(0,Assumptions!$B$11+INDEX(Assumptions!$A$24:$B$35,MATCH(B9,Assumptions!$A$24:$A$35,0),2)) -> 3 | D9: =Assumptions!$B$12*(1+Assumptions!$B$13)^(A9-2027) -> 11.400931 | E9: =C9*D9 -> 34.202792
A10: 2036 | B10: =29+A10-2031 -> 34 | C10: =MAX(0,Assumptions!$B$11+INDEX(Assumptions!$A$24:$B$35,MATCH(B10,Assumptions!$A$24:$A$35,0),2)) -> 2.3 | D10: =Assumptions!$B$12*(1+Assumptions!$B$13)^(A10-2027) -> 11.742959 | E10: =C10*D10 -> 27.008805
A11: 2037 | B11: =29+A11-2031 -> 35 | C11: =MAX(0,Assumptions!$B$11+INDEX(Assumptions!$A$24:$B$35,MATCH(B11,Assumptions!$A$24:$A$35,0),2)) -> 1.6 | D11: =Assumptions!$B$12*(1+Assumptions!$B$13)^(A11-2027) -> 12.095247 | E11: =C11*D11 -> 19.352396
A12: 2038 | B12: =29+A12-2031 -> 36 | C12: =MAX(0,Assumptions!$B$11+INDEX(Assumptions!$A$24:$B$35,MATCH(B12,Assumptions!$A$24:$A$35,0),2)) -> 0.9 | D12: =Assumptions!$B$12*(1+Assumptions!$B$13)^(A12-2027) -> 12.458105 | E12: =C12*D12 -> 11.212294
A13: Term (years) | B13: =Assumptions!$B$19 -> 8
A14: Total projected value over the term ($M) | B14: =SUM(E5:E12) -> 291.9778
A15: Share of that value actually captured | B15: =Assumptions!$B$20 -> 1
A16: Average annual value used for 2031 and 2032 ($M) | B16: =B14*B15/B13 -> 36.497225
A17: Note: the term only runs eight years because WAR goes to zero on this curve. Lengthen it and the average annual value falls.

Sheet Model
A1: Year by year build, 2027 through 2032
A2: Surplus value asks what he produced against what he was paid. Savings asks what the extension changed against the control years the Cubs already held. They are different questions with different answers.
A4: Year | B4: Age | C4: Status | D4: Projected WAR | E4: $ per win ($M) | F4: Market value ($M) | G4: Salary paid ($M) | H4: Cost with no extension ($M) | I4: Surplus value ($M) | J4: Savings vs no extension ($M) | K4: Discount factor | L4: PV of surplus ($M) | M4: PV of savings ($M)
A5: 2027 | B5: =25+A5-2027 -> 25 | C5: pre-arb | D5: =MAX(0,Assumptions!$B$11+INDEX(Assumptions!$A$24:$B$35,MATCH(B5,Assumptions!$A$24:$A$35,0),2)) -> 6.5 | E5: =Assumptions!$B$12*(1+Assumptions!$B$13)^(A5-2027) -> 9 | F5: =D5*E5 -> 58.5 | G5: 10 | H5: =IF(C5="pre-arb",Assumptions!$B$15,IF(C5="free agent",'FA deal'!$B$16,IF(C5="arb1",Assumptions!$B$16,IF(C5="arb2",Assumptions!$B$17,Assumptions!$B$18))*F5)) -> 1 | I5: =F5-G5 -> 48.5 | J5: =H5-G5 -> -9 | K5: =1/(1+Assumptions!$B$14)^(A5-Assumptions!$B$8) -> 0.94339623 | L5: =I5*K5 -> 45.754717 | M5: =J5*K5 -> -8.490566
A6: 2028 | B6: =25+A6-2027 -> 26 | C6: arb1 | D6: =MAX(0,Assumptions!$B$11+INDEX(Assumptions!$A$24:$B$35,MATCH(B6,Assumptions!$A$24:$A$35,0),2)) -> 6.8 | E6: =Assumptions!$B$12*(1+Assumptions!$B$13)^(A6-2027) -> 9.27 | F6: =D6*E6 -> 63.036 | G6: 10 | H6: =IF(C6="pre-arb",Assumptions!$B$15,IF(C6="free agent",'FA deal'!$B$16,IF(C6="arb1",Assumptions!$B$16,IF(C6="arb2",Assumptions!$B$17,Assumptions!$B$18))*F6)) -> 15.759 | I6: =F6-G6 -> 53.036 | J6: =H6-G6 -> 5.759 | K6: =1/(1+Assumptions!$B$14)^(A6-Assumptions!$B$8) -> 0.88999644 | L6: =I6*K6 -> 47.201851 | M6: =J6*K6 -> 5.1254895
A7: 2029 | B7: =25+A7-2027 -> 27 | C7: arb2 | D7: =MAX(0,Assumptions!$B$11+INDEX(Assumptions!$A$24:$B$35,MATCH(B7,Assumptions!$A$24:$A$35,0),2)) -> 6.8 | E7: =Assumptions!$B$12*(1+Assumptions!$B$13)^(A7-2027) -> 9.5481 | F7: =D7*E7 -> 64.92708 | G7: 10 | H7: =IF(C7="pre-arb",Assumptions!$B$15,IF(C7="free agent",'FA deal'!$B$16,IF(C7="arb1",Assumptions!$B$16,IF(C7="arb2",Assumptions!$B$17,Assumptions!$B$18))*F7)) -> 25.970832 | I7: =F7-G7 -> 54.92708 | J7: =H7-G7 -> 15.970832 | K7: =1/(1+Assumptions!$B$14)^(A7-Assumptions!$B$8) -> 0.83961928 | L7: =I7*K7 -> 46.117836 | M7: =J7*K7 -> 13.409419
A8: 2030 | B8: =25+A8-2027 -> 28 | C8: arb3 | D8: =MAX(0,Assumptions!$B$11+INDEX(Assumptions!$A$24:$B$35,MATCH(B8,Assumptions!$A$24:$A$35,0),2)) -> 6.4 | E8: =Assumptions!$B$12*(1+Assumptions!$B$13)^(A8-2027) -> 9.834543 | F8: =D8*E8 -> 62.941075 | G8: 20 | H8: =IF(C8="pre-arb",Assumptions!$B$15,IF(C8="free agent",'FA deal'!$B$16,IF(C8="arb1",Assumptions!$B$16,IF(C8="arb2",Assumptions!$B$17,Assumptions!$B$18))*F8)) -> 37.764645 | I8: =F8-G8 -> 42.941075 | J8: =H8-G8 -> 17.764645 | K8: =1/(1+Assumptions!$B$14)^(A8-Assumptions!$B$8) -> 0.79209366 | L8: =I8*K8 -> 34.013354 | M8: =J8*K8 -> 14.071263
A9: 2031 | B9: =25+A9-2027 -> 29 | C9: free agent | D9: =MAX(0,Assumptions!$B$11+INDEX(Assumptions!$A$24:$B$35,MATCH(B9,Assumptions!$A$24:$A$35,0),2)) -> 5.8 | E9: =Assumptions!$B$12*(1+Assumptions!$B$13)^(A9-2027) -> 10.129579 | F9: =D9*E9 -> 58.75156 | G9: 30 | H9: =IF(C9="pre-arb",Assumptions!$B$15,IF(C9="free agent",'FA deal'!$B$16,IF(C9="arb1",Assumptions!$B$16,IF(C9="arb2",Assumptions!$B$17,Assumptions!$B$18))*F9)) -> 36.497225 | I9: =F9-G9 -> 28.75156 | J9: =H9-G9 -> 6.4972247 | K9: =1/(1+Assumptions!$B$14)^(A9-Assumptions!$B$8) -> 0.74725817 | L9: =I9*K9 -> 21.484838 | M9: =J9*K9 -> 4.8551043
A10: 2032 | B10: =25+A10-2027 -> 30 | C10: free agent | D10: =MAX(0,Assumptions!$B$11+INDEX(Assumptions!$A$24:$B$35,MATCH(B10,Assumptions!$A$24:$A$35,0),2)) -> 5.1 | E10: =Assumptions!$B$12*(1+Assumptions!$B$13)^(A10-2027) -> 10.433467 | F10: =D10*E10 -> 53.21068 | G10: 30 | H10: =IF(C10="pre-arb",Assumptions!$B$15,IF(C10="free agent",'FA deal'!$B$16,IF(C10="arb1",Assumptions!$B$16,IF(C10="arb2",Assumptions!$B$17,Assumptions!$B$18))*F10)) -> 36.497225 | I10: =F10-G10 -> 23.21068 | J10: =H10-G10 -> 6.4972247 | K10: =1/(1+Assumptions!$B$14)^(A10-Assumptions!$B$8) -> 0.70496054 | L10: =I10*K10 -> 16.362614 | M10: =J10*K10 -> 4.5802871
A11: Total | D11: =SUM(D5:D10) -> 37.4 | F11: =SUM(F5:F10) -> 361.3664 | G11: =SUM(G5:G10) -> 110 | H11: =SUM(H5:H10) -> 153.48893 | I11: =SUM(I5:I10) -> 251.3664 | J11: =SUM(J5:J10) -> 43.488927 | L11: =SUM(L5:L10) -> 210.93521 | M11: =SUM(M5:M10) -> 33.550996
A13: Signing bonus paid in 2026 ($M), an extra cost that exists only because the extension exists | B13: =-Assumptions!$B$6 -> -5
